mylabs_mcp/__init__.py
mylabs_mcp/projectten_expert/__init__.py
mylabs_mcp/projectten_expert/server.py
mylabs_mcp_projectten_expert-0.1.0.dist-info/METADATA
mylabs_mcp_projectten_expert-0.1.0.dist-info/WHEEL
mylabs_mcp_projectten_expert-0.1.0.dist-info/entry_points.txt
mylabs_mcp_projectten_expert-0.1.0.dist-info/RECORD
