Metadata-Version: 2.4
Name: mylabs-mcp.projectten-expert
Version: 0.1.0
Summary: Project Ten Model Context Protocol (MCP) server
Project-URL: Homepage, https://github.com/scottschreckengaust/mcpmonorepo
Project-URL: Repository, https://github.com/scottschreckengaust/mcpmonorepo.git
Author-email: Scott Schreckengaust <scottschreckengaust@users.noreply.github.com>
Requires-Python: >=3.13
Requires-Dist: mcp[cli]>=1.3.0
Requires-Dist: pydantic>=2.10.6
